threadfunction/__init__.py
threadfunction-1.0.0.dist-info/LICENSE
threadfunction-1.0.0.dist-info/METADATA
threadfunction-1.0.0.dist-info/WHEEL
threadfunction-1.0.0.dist-info/top_level.txt
threadfunction-1.0.0.dist-info/RECORD
