Metadata-Version: 2.1
Name: threadfunction
Version: 1.0.0
Summary: a library for ThreadFunction Decorator
Home-page: https://github.com/ixjx/threadfunction
Author: shurrik
Author-email: vissk1@163.com
License: MIT License
Platform: UNKNOWN
Classifier: Programming Language :: Python :: 3
Classifier: License :: OSI Approved :: MIT License
Classifier: Operating System :: OS Independent
License-File: LICENSE
